qbraid/__init__.py
qbraid/_about.py
qbraid/_caching.py
qbraid/_display.py
qbraid/_entrypoints.py
qbraid/_logging.py
qbraid/_version.py
qbraid/exceptions.py
qbraid/py.typed
qbraid/interface/__init__.py
qbraid/interface/circuit_equality.py
qbraid/interface/random/__init__.py
qbraid/interface/random/cirq_random.py
qbraid/interface/random/ionq_random.py
qbraid/interface/random/qasm3_random.py
qbraid/interface/random/qiskit_random.py
qbraid/interface/random/random.py
qbraid/passes/__init__.py
qbraid/passes/exceptions.py
qbraid/passes/qasm/__init__.py
qbraid/passes/qasm/compat.py
qbraid/passes/qasm/decompose.py
qbraid/programs/__init__.py
qbraid/programs/_import.py
qbraid/programs/alias_manager.py
qbraid/programs/exceptions.py
qbraid/programs/experiment.py
qbraid/programs/loader.py
qbraid/programs/program.py
qbraid/programs/registry.py
qbraid/programs/spec.py
qbraid/programs/typer.py
qbraid/programs/ahs/__init__.py
qbraid/programs/ahs/_model.py
qbraid/programs/ahs/braket_ahs.py
qbraid/programs/annealing/__init__.py
qbraid/programs/annealing/_model.py
qbraid/programs/annealing/cpp_pyqubo.py
qbraid/programs/annealing/qubo.py
qbraid/programs/gate_model/__init__.py
qbraid/programs/gate_model/_model.py
qbraid/programs/gate_model/braket.py
qbraid/programs/gate_model/cirq.py
qbraid/programs/gate_model/cudaq.py
qbraid/programs/gate_model/ionq.py
qbraid/programs/gate_model/pennylane.py
qbraid/programs/gate_model/pyquil.py
qbraid/programs/gate_model/pytket.py
qbraid/programs/gate_model/qasm2.py
qbraid/programs/gate_model/qasm3.py
qbraid/programs/gate_model/qiskit.py
qbraid/runtime/__init__.py
qbraid/runtime/_display.py
qbraid/runtime/device.py
qbraid/runtime/enums.py
qbraid/runtime/exceptions.py
qbraid/runtime/job.py
qbraid/runtime/loader.py
qbraid/runtime/noise.py
qbraid/runtime/options.py
qbraid/runtime/postprocess.py
qbraid/runtime/profile.py
qbraid/runtime/provider.py
qbraid/runtime/result.py
qbraid/runtime/result_data.py
qbraid/runtime/aws/__init__.py
qbraid-0.10.0.dist-info/licenses/LICENSE
qbraid-0.10.0.dist-info/METADATA
qbraid-0.10.0.dist-info/WHEEL
qbraid-0.10.0.dist-info/entry_points.txt
qbraid-0.10.0.dist-info/top_level.txt
qbraid-0.10.0.dist-info/RECORD
