Metadata-Version: 2.4
Name: qbraid
Version: 0.10.0
Summary: Platform-agnostic quantum runtime framework.
Author: qBraid Development Team
Author-email: contact@qbraid.com
License-Expression: Apache-2.0
Project-URL: Homepage, https://sdk.qbraid.com/
Project-URL: Documentation, https://docs.qbraid.com/sdk
Project-URL: Source Code, https://github.com/qBraid/qBraid
Project-URL: Bug Tracker, https://github.com/qBraid/qBraid/issues
Project-URL: Discord, https://discord.gg/TPBU2sa8Et
Project-URL: Launch on Lab, https://account.qbraid.com/?gitHubUrl=https://github.com/qBraid/qBraid.git
Keywords: qbraid,quantum,openqasm,runtime
Classifier: Development Status :: 5 - Production/Stable
Classifier: Intended Audience :: Developers
Classifier: Intended Audience :: Science/Research
Classifier: Natural Language :: English
Classifier: Programming Language :: Python
Classifier: Programming Language :: Python :: 3
Classifier: Programming Language :: Python :: 3.10
Classifier: Programming Language :: Python :: 3.11
Classifier: Programming Language :: Python :: 3.12
Classifier: Programming Language :: Python :: 3.13
Classifier: Programming Language :: Python :: 3 :: Only
Classifier: Topic :: Software Development
Classifier: Topic :: Scientific/Engineering
Classifier: Topic :: Scientific/Engineering :: Physics
Classifier: Typing :: Typed
Classifier: Operating System :: Microsoft :: Windows
Classifier: Operating System :: POSIX
Classifier: Operating System :: Unix
Classifier: Operating System :: MacOS
Requires-Python: >=3.10
License-File: LICENSE
Requires-Dist: rustworkx>=0.15.0
Requires-Dist: numpy>=1.17
Requires-Dist: openqasm3[parser]>=0.4.0
Requires-Dist: qbraid-core>=0.1.39
Requires-Dist: pydantic<=2.11.1,>2.0.0
Requires-Dist: pydantic-core
Requires-Dist: typing-extensions>=4.0.0
Requires-Dist: pyqasm<1.1.0,>=0.5.0
Provides-Extra: azure
Requires-Dist: azure-quantum<2.3,>=2.0; extra == "azure"
Requires-Dist: azure-storage-blob<13.0,>=12.20; extra == "azure"
Requires-Dist: azure-identity<2.0,>=1.17; extra == "azure"
Provides-Extra: bloqade
Requires-Dist: bloqade-analog<0.17.0,>=0.16.1; extra == "bloqade"
Provides-Extra: braket
Requires-Dist: amazon-braket-sdk<1.103.0,>=1.83.0; extra == "braket"
Requires-Dist: pytket-braket<0.45,>=0.30; extra == "braket"
Provides-Extra: cirq
Requires-Dist: cirq-core<1.7,>=1.3; extra == "cirq"
Requires-Dist: cirq-ionq<1.7,>=1.3; extra == "cirq"
Requires-Dist: ply>=3.6; extra == "cirq"
Requires-Dist: attrs>=21.3.0; extra == "cirq"
Provides-Extra: cudaq
Requires-Dist: cudaq>=0.9.0; extra == "cudaq"
Provides-Extra: ionq
Requires-Dist: qiskit-ionq>=0.5.12; extra == "ionq"
Provides-Extra: oqc
Requires-Dist: oqc-qcaas-client>=3.11.0; extra == "oqc"
Provides-Extra: pennylane
Requires-Dist: pennylane<0.42; extra == "pennylane"
Provides-Extra: pyqubo
Requires-Dist: pyqubo>=1.4.0; extra == "pyqubo"
Provides-Extra: pyquil
Requires-Dist: pyquil>=4.4; extra == "pyquil"
Requires-Dist: qcs-sdk-python<0.21.20,>=0.21.12; extra == "pyquil"
Provides-Extra: pytket
Requires-Dist: pytket>=1.31; extra == "pytket"
Provides-Extra: qir
Requires-Dist: qbraid-qir<=0.4.0,>=0.2.0; extra == "qir"
Requires-Dist: qbraid-core[runner]>=0.1.39; extra == "qir"
Provides-Extra: qiskit
Requires-Dist: qiskit<3.0,>=1.0; extra == "qiskit"
Requires-Dist: qiskit-ibm-runtime<0.42,>=0.39.0; extra == "qiskit"
Requires-Dist: qiskit-qasm3-import>=0.5.1; extra == "qiskit"
Requires-Dist: packaging>=20.0; extra == "qiskit"
Provides-Extra: quera
Requires-Dist: flair-visual[vis]>=0.5.3; extra == "quera"
Requires-Dist: pandas; extra == "quera"
Provides-Extra: visualization
Requires-Dist: ipython; extra == "visualization"
Requires-Dist: matplotlib; extra == "visualization"
Requires-Dist: pylatexenc; extra == "visualization"
Requires-Dist: ipympl; extra == "visualization"
Requires-Dist: pyqasm[visualization]; extra == "visualization"
Dynamic: license-file
